google_drive_api/__init__.py
google_drive_api/api.py
google_drive_api/auth.py
google_drive_api/exceptions.py
google_drive_api/model.py
google_drive_api/py.typed
python_google_drive_api-0.0.2.dist-info/LICENSE
python_google_drive_api-0.0.2.dist-info/METADATA
python_google_drive_api-0.0.2.dist-info/WHEEL
python_google_drive_api-0.0.2.dist-info/top_level.txt
python_google_drive_api-0.0.2.dist-info/RECORD
