Metadata-Version: 2.2
Name: python-google-drive-api
Version: 0.0.2
Summary: A python client library for Google Drive API
Author-email: tronikos <tronikos@gmail.com>
License: Apache-2.0
Project-URL: Homepage, https://github.com/tronikos/python-google-drive-api
Project-URL: Bug Tracker, https://github.com/tronikos/python-google-drive-api/issues
Requires-Python: >=3.10
License-File: LICENSE
Requires-Dist: aiohttp>=3.8
Requires-Dist: mashumaro>=3.12
Provides-Extra: dev
Requires-Dist: pytest>=7; extra == "dev"
